{ "id": "content_columns", "type": "SharedSlice", "name": "Content Columns", "variations": [{ "id": "selectionGuide", "name": "Selection Guide", "primary": { "eyebrow": { "type": "Text" }, "title": { "type": "Text" }, "body": { "type": "Text" }, "panelTitle": { "type": "Text" }, "panelBody": { "type": "Text" } }, "items": { "title": { "type": "Text" }, "text": { "type": "Text" } } }, { "id": "mission", "name": "Mission", "primary": { "eyebrow": { "type": "Text" }, "title": { "type": "Text" }, "body": { "type": "Text" }, "panelTitle": { "type": "Text" }, "panelBody": { "type": "Text" } }, "items": { "title": { "type": "Text" }, "text": { "type": "Text" } } }, { "id": "operatingModel", "name": "Operating Model", "primary": { "eyebrow": { "type": "Text" }, "title": { "type": "Text" }, "body": { "type": "Text" }, "panelTitle": { "type": "Text" }, "panelBody": { "type": "Text" } }, "items": { "title": { "type": "Text" }, "text": { "type": "Text" } } }] }
